kiarina/utils/common/__init__.py
kiarina/utils/common/py.typed
kiarina/utils/common/_helpers/__init__.py
kiarina/utils/common/_helpers/import_object.py
kiarina/utils/common/_helpers/parse_config_string.py
kiarina/utils/common/_types/__init__.py
kiarina/utils/common/_types/config_str.py
kiarina/utils/common/_types/import_path.py
kiarina_utils_common-1.35.0.dist-info/METADATA
kiarina_utils_common-1.35.0.dist-info/WHEEL
kiarina_utils_common-1.35.0.dist-info/RECORD
